{
  "HeWeather6": [
    {
      "basic": {
        "cid": "CN101010100",
        "location": "北京",
        "parent_city": "北京",
        "admin_area": "北京",
        "cnty": "中国",
        "lat": "39.90498734",
        "lon": "116.4052887",
        "tz": "+8.00"
      },
      "update": {
        "loc": "2019-12-15 19:56",
        "utc": "2019-12-15 11:56"
      },
      "status": "ok",
      "now": {
        "cloud": "99",
        "cond_code": "101",
        "cond_txt": "多云",
        "fl": "-1",
        "hum": "52",
        "pcpn": "0.0",
        "pres": "1022",
        "tmp": "2",
        "vis": "15",
        "wind_deg": "258",
        "wind_dir": "西南风",
        "wind_sc": "2",
        "wind_spd": "7"
      }
    }
  ]
}
